README.md
setup.py
tflit/__init__.py
tflit/_old_tflite_install.py
tflit/core.py
tflit/install.py
tflit/tflite_install.py
tflit/util.py
tflit.egg-info/PKG-INFO
tflit.egg-info/SOURCES.txt
tflit.egg-info/dependency_links.txt
tflit.egg-info/requires.txt
tflit.egg-info/top_level.txt
tflit/example/__init__.py
tflit/example/basic.py
tflit/example/basic.tflite