Metadata-Version: 2.1
Name: tflit
Version: 0.1.2
Summary: tflite_runtime, but easier.
Home-page: https://github.com/beasteers/tflit
Author: Bea Steers
Author-email: bea.steers@gmail.com
License: MIT License
Keywords: tflite runtime tensorflow keras deep machine learning model edge embedded compute cnn
Platform: UNKNOWN
Provides-Extra: tests
